pecking/__init__.py
pecking/_mask_skimmed_rows.py
pecking/_peckplot.py
pecking/_robust_groupby.py
pecking/_skim_highest.py
pecking/_skim_lowest.py
pecking-0.2.2.dist-info/LICENSE
pecking-0.2.2.dist-info/METADATA
pecking-0.2.2.dist-info/WHEEL
pecking-0.2.2.dist-info/top_level.txt
pecking-0.2.2.dist-info/RECORD
