Metadata-Version: 2.1
Name: pecking
Version: 0.2.2
Summary: pecking identifies the set of lowest-ranked groups and set of highest-ranked groups in a dataset using nonparametric statistical tests
Author-email: Matthew Andres Moreno <m.more500@gmail.com>
License: MIT license
Project-URL: homepage, https://github.com/mmore500/pytest
Project-URL: documentation, https://github.com/mmore500/pytest
Project-URL: repository, https://github.com/mmore500/pytest
Project-URL: tracker, https://github.com/mmore500/pytest/issues
Classifier: Development Status :: 3 - Alpha
Classifier: Intended Audience :: Developers
Classifier: Topic :: Software Development :: Libraries :: Python Modules
Classifier: License :: OSI Approved :: MIT License
Classifier: Programming Language :: Python :: 3
Classifier: Programming Language :: Python :: 3.8
Classifier: Programming Language :: Python :: 3.9
Classifier: Programming Language :: Python :: 3.10
Classifier: Programming Language :: Python :: 3.11
Classifier: Programming Language :: Python :: 3.12
Requires-Python: >=3.8
License-File: LICENSE
Requires-Dist: backstrip >=0.2.3
Requires-Dist: numpy
Requires-Dist: pandas
Requires-Dist: scipy
Requires-Dist: seaborn
Provides-Extra: dev
Requires-Dist: black ==22.10.0 ; extra == 'dev'
Requires-Dist: bump2version ==1.0.1 ; extra == 'dev'
Requires-Dist: isort ==5.12.0 ; extra == 'dev'
Requires-Dist: matplotlib ==3.7.5 ; extra == 'dev'
Requires-Dist: pip-tools ==7.3.0 ; extra == 'dev'
Requires-Dist: pytest ==6.2.5 ; extra == 'dev'
Requires-Dist: ruff ==0.1.11 ; extra == 'dev'
